Workbook

Sheet Overview
A1: StyleMint Mobile — Team Work Tracker
A2: API integration backlog by owner · status from a code audit of the dev branch · 6 July 2026
A3: Workflow: Not started → In progress → In review (Smit) → In QA → Completed. 'Blocked' = built, waiting on backend.
A5: Person | B5: Owns | C5: Items | D5: Not started | E5: In progress | F5: Blocked | G5: In review | H5: In QA | I5: Completed | J5: Parked
A6: Cilus | B6: Creator flow | C6: 10 | D6: =COUNTIF('Cilus'!F7:F16,"Not started") | E6: =COUNTIF('Cilus'!F7:F16,"In progress") | F6: =COUNTIF('Cilus'!F7:F16,"Blocked") | G6: =COUNTIF('Cilus'!F7:F16,"In review") | H6: =COUNTIF('Cilus'!F7:F16,"In QA") | I6: =COUNTIF('Cilus'!F7:F16,"Completed") | J6: =COUNTIF('Cilus'!F7:F16,"Parked")
A7: Sailesh | B7: Customer flow | C7: 14 | D7: =COUNTIF('Sailesh'!F7:F20,"Not started") | E7: =COUNTIF('Sailesh'!F7:F20,"In progress") | F7: =COUNTIF('Sailesh'!F7:F20,"Blocked") | G7: =COUNTIF('Sailesh'!F7:F20,"In review") | H7: =COUNTIF('Sailesh'!F7:F20,"In QA") | I7: =COUNTIF('Sailesh'!F7:F20,"Completed") | J7: =COUNTIF('Sailesh'!F7:F20,"Parked")
A8: Savyata | B8: Vendor flow | C8: 12 | D8: =COUNTIF('Savyata'!F7:F18,"Not started") | E8: =COUNTIF('Savyata'!F7:F18,"In progress") | F8: =COUNTIF('Savyata'!F7:F18,"Blocked") | G8: =COUNTIF('Savyata'!F7:F18,"In review") | H8: =COUNTIF('Savyata'!F7:F18,"In QA") | I8: =COUNTIF('Savyata'!F7:F18,"Completed") | J8: =COUNTIF('Savyata'!F7:F18,"Parked")
A9: Smit | B9: PM / Integration Lead | C9: 6 | D9: =COUNTIF('Smit'!F7:F12,"Not started") | E9: =COUNTIF('Smit'!F7:F12,"In progress") | F9: =COUNTIF('Smit'!F7:F12,"Blocked") | G9: =COUNTIF('Smit'!F7:F12,"In review") | H9: =COUNTIF('Smit'!F7:F12,"In QA") | I9: =COUNTIF('Smit'!F7:F12,"Completed") | J9: =COUNTIF('Smit'!F7:F12,"Parked")
A10: TOTAL | B10: all roles | C10: =SUM(C6:C9) | D10: =SUM(D6:D9) | E10: =SUM(E6:E9) | F10: =SUM(F6:F9) | G10: =SUM(G6:G9) | H10: =SUM(H6:H9) | I10: =SUM(I6:I9) | J10: =SUM(J6:J9)
A13: What the statuses mean
A14: Not started | B14: Work has not begun. If 'Waiting on = Backend', it can't begin until backend provides the endpoint.
A15: In progress | B15: The developer is actively building it.
A16: Blocked | B16: Built on our side, but stuck waiting on the backend to confirm or add a server endpoint. Not an app-team delay.
A17: In review | B17: Developer finished; awaiting Smit's review before it goes to QA.
A18: In QA | B18: Passed your review and is being tested by QA.
A19: Completed | B19: QA has signed off. This is the ONLY status that counts as truly done.
A20: Parked | B20: Deliberately deferred this cycle by a product decision.
A22: Note: status reflects what is built in the code today. Nothing in the three app flows is 'Completed' yet because none has passed QA — the finished work is sitting at 'In review'. Advance items to In QA / Completed as they clear. 'Waiting on' shows who must act next: Backend, App team (us), Smit (review), or QA.

Sheet Smit
A1: Smit
A2: PM / Integration Lead · task IDs P# · as of 6 Jul 2026
A4: ="Completed "&COUNTIF(F7:F12,"Completed")&" "&"In QA "&COUNTIF(F7:F12,"In QA")&" "&"In review "&COUNTIF(F7:F12,"In review")&" "&"In progress "&COUNTIF(F7:F12,"In progress")&" "&"Blocked "&COUNTIF(F7:F12,"Blocked")&" "&"Not started "&COUNTIF(F7:F12,"Not started")&" "&"Parked "&COUNTIF(F7:F12,"Parked")
A6: ID | B6: Feature | C6: What this task is | D6: Type of work | E6: Sprint | F6: Status | G6: Waiting on | H6: Where it stands
A7: P3 | B7: Tracking board | C7: Set up a shared tracking board and give every task an ID and an owner. | D7: Coordination | E7: — | F7: Completed | G7: Nothing | H7: This workbook.
A8: P1 | B8: Backend address reconciliation | C8: Run one working session with the backend team to confirm the correct server address for every uncertain endpoint. This single step unblocks ~22 tasks across all three apps. | D8: Coordination | E8: — | F8: In progress | G8: Backend | H8: Several already confirmed & shipped (vendor partnerships, products, KYC); the rest pending.
A9: P4 | B9: Quality gates before merge | C9: Enforce quality on every merge: code must pass the analyzer with zero errors, and each flow is walked through against the live test server. | D9: Coordination | E9: — | F9: In progress | G9: Nothing | H9: Analyzer gate held at 0 errors through every merge; live walk-through sign-off still to be done.
A10: P6 | B10: Daily blocker triage | C10: Run daily check-ins during the busy 'confirm the addresses' phase to clear blockers quickly. | D10: Coordination | E10: — | F10: In progress | G10: Nothing | H10: Ongoing through Sprint 2.
A11: P2 | B11: Raise new-backend requests early | C11: File the three requests for brand-new backend work early (Brand Studio, reel-import search/history, first-run profile signal) because they take longest. | D11: Coordination | E11: — | F11: Not started | G11: Nothing | H11: External action — confirm the tickets are filed.
A12: P5 | B12: Chase notifications bug | C12: Follow up with backend on the empty-inbox login bug affecting notifications. | D12: Coordination | E12: — | F12: In progress | G12: Backend | H12: Notifications wired in the app; confirm the backend bug is closed.

Sheet Cilus
A1: Cilus
A2: Creator flow · task IDs CR# · as of 6 Jul 2026
A4: ="Completed "&COUNTIF(F7:F16,"Completed")&" "&"In QA "&COUNTIF(F7:F16,"In QA")&" "&"In review "&COUNTIF(F7:F16,"In review")&" "&"In progress "&COUNTIF(F7:F16,"In progress")&" "&"Blocked "&COUNTIF(F7:F16,"Blocked")&" "&"Not started "&COUNTIF(F7:F16,"Not started")&" "&"Parked "&COUNTIF(F7:F16,"Parked")
A6: ID | B6: Feature | C6: What this task is | D6: Type of work | E6: Sprint | F6: Status | G6: Waiting on | H6: Where it stands
A7: CR1 | B7: Analytics dashboard | C7: Connect the creator's analytics screen (profile views, earnings trend, top reels & products) to real server data, replacing the hard-coded sample numbers. | D7: App-side only | E7: Sprint 1 | F7: In review | G7: Smit | H7: Team finished coding — awaiting your review, then QA.
A8: CR3 | B8: Creator profile | C8: Load and save the creator's profile (bio, niche, links) from the server so edits actually persist instead of only living on the phone. | D8: App-side only | E8: Sprint 1 | F8: In review | G8: Smit | H8: Team finished coding — awaiting your review, then QA.
A9: CR4 | B9: Reels list | C9: Give the creator's reels list its own connection to the server (decided it needs its own rather than reusing the customer feed). | D9: App-side only | E9: Sprint 1 | F9: In review | G9: Smit | H9: Team finished coding — awaiting your review, then QA.
A10: CR9 | B10: Tips: history & balance | C10: Show the creator's tip history and current tip balance from the server. | D10: Needs backend path | E10: Sprint 2 | F10: Blocked | G10: Backend | H10: Built our side; tips history/balance server addresses not confirmed.
A11: CR2 | B11: Help & support | C11: Connect the support screen so creators can view and raise help tickets. The screen exists but isn't wired to anything yet. | D11: App-side only | E11: Sprint 1 | F11: Not started | G11: App team | H11: Our team can start now — no backend dependency.
A12: CR5 | B12: Sign-up: ID upload | C12: Let applicants upload identity documents during creator sign-up. | D12: Needs backend path | E12: Sprint 2 | F12: Not started | G12: Backend | H12: Can't start until the upload address exists in the backend spec.
A13: CR6 | B13: Payout methods | C13: Let creators view and add payout methods (bank / e-wallet). | D13: Needs backend path | E13: Sprint 2 | F13: Not started | G13: Backend | H13: Waiting on the correct payout-methods address.
A14: CR7 | B14: Active partnerships | C14: Show only the creator's currently-active brand partnerships. | D14: Needs backend path | E14: Sprint 2 | F14: Not started | G14: Backend | H14: Needs a dedicated endpoint or status filter from backend.
A15: CR8 | B15: Reel studio: delete draft | C15: Let creators delete a saved reel draft. | D15: Needs backend path | E15: Sprint 2 | F15: Not started | G15: Backend | H15: Delete address doesn't match what the server offers.
A16: CR10 | B16: Reel import: tag & history | C16: When importing a reel, let creators search products to tag and see their past imports. | D16: Needs new backend | E16: Sprint 3 | F16: Not started | G16: Backend | H16: Needs brand-new backend endpoints.

Sheet Sailesh
A1: Sailesh
A2: Customer flow · task IDs C# · as of 6 Jul 2026
A4: ="Completed "&COUNTIF(F7:F20,"Completed")&" "&"In QA "&COUNTIF(F7:F20,"In QA")&" "&"In review "&COUNTIF(F7:F20,"In review")&" "&"In progress "&COUNTIF(F7:F20,"In progress")&" "&"Blocked "&COUNTIF(F7:F20,"Blocked")&" "&"Not started "&COUNTIF(F7:F20,"Not started")&" "&"Parked "&COUNTIF(F7:F20,"Parked")
A6: ID | B6: Feature | C6: What this task is | D6: Type of work | E6: Sprint | F6: Status | G6: Waiting on | H6: Where it stands
A7: C1 | B7: My Orders | C7: Switch the orders screens (list, detail, cancel, return) from sample data to the real server so customers see their actual orders. | D7: App-side only | E7: Sprint 1 | F7: In QA | G7: QA | H7: Reviewed by Smit — passed to QA.
A8: C3 | B8: Payment methods | C8: Remove the temporary test data so saved cards load from the server. | D8: App-side only | E8: Sprint 1 | F8: In QA | G8: QA | H8: Reviewed by Smit — passed to QA.
A9: C4 | B9: Saved items | C9: Remove the temporary test data so saved / wishlist items load from the server. | D9: App-side only | E9: Sprint 1 | F9: In QA | G9: QA | H9: Reviewed by Smit — passed to QA.
A10: C5 | B10: Shipping addresses | C10: Remove the temporary test data so addresses load from the server. | D10: App-side only | E10: Sprint 1 | F10: In QA | G10: QA | H10: Reviewed by Smit — passed to QA.
A11: C11 | B11: Notifications inbox | C11: Confirm the notifications inbox points at the correct server address. | D11: Needs backend path | E11: Sprint 2 | F11: In QA | G11: QA | H11: Reviewed by Smit — passed to QA.
A12: C6 | B12: My profile / account | C12: Finish the profile screen: let users upload a profile photo and complete the account-deletion wiring. | D12: App-side only | E12: Sprint 1 | F12: In progress | G12: App team | H12: Account delete done; profile-photo upload still being built.
A13: C7 | B13: Discovery: related & save | C13: Show 'related products' on a product page and let users save an item for later. | D13: Needs backend path | E13: Sprint 2 | F13: Blocked | G13: Backend | H13: Save works; 'related products' address still needs confirming.
A14: C12 | B14: Social: feed, stories, drops | C14: Enable sharing a post, deleting a story, and drop-party invite / QR scan. | D14: Needs backend path | E14: Sprint 2 | F14: Blocked | G14: Backend | H14: Screens built; several server addresses to confirm.
A15: C13 | B15: Social: group cart & co-watch | C15: Enable shared group-cart add/remove and co-watch session details & reactions. | D15: Needs backend path | E15: Sprint 2 | F15: Blocked | G15: Backend | H15: Screens built; server addresses to confirm.
A16: C8 | B16: Product reviews summary | C16: Show a ratings summary (average stars, counts) on product pages. | D16: Needs backend path | E16: Sprint 2 | F16: Not started | G16: Backend | H16: No summary endpoint — decide server-side vs in-app calc.
A17: C9 | B17: App language setting | C17: Save and load the user's chosen language from the server. | D17: Needs backend path | E17: Sprint 2 | F17: Not started | G17: Backend | H17: Language endpoint isn't available.
... A20: C2 | B20: Customer reels feed | C20: Switch the reels feed from sample data to the real server. | D20: Product decision | E20: Parked | F20: Parked | G20: Decision | H20: Deliberately kept on sample data this cycle until the reel pipeline can seed real content.

Sheet Savyata
A1: Savyata
A2: Vendor flow · task IDs V# · as of 6 Jul 2026
A4: ="Completed "&COUNTIF(F7:F18,"Completed")&" "&"In QA "&COUNTIF(F7:F18,"In QA")&" "&"In review "&COUNTIF(F7:F18,"In review")&" "&"In progress "&COUNTIF(F7:F18,"In progress")&" "&"Blocked "&COUNTIF(F7:F18,"Blocked")&" "&"Not started "&COUNTIF(F7:F18,"Not started")&" "&"Parked "&COUNTIF(F7:F18,"Parked")
A6: ID | B6: Feature | C6: What this task is | D6: Type of work | E6: Sprint | F6: Status | G6: Waiting on | H6: Where it stands
A7: V1 | B7: Customer inquiries | C7: Complete the connection so vendors can see customer product inquiries in-app. | D7: App-side only | E7: Sprint 1 | F7: In review | G7: Smit | H7: Team finished coding — awaiting your review, then QA.
A8: V2 | B8: Analytics dashboard | C8: Connect the vendor analytics screen (sales, revenue, commissions) to live server data. | D8: App-side only | E8: Sprint 1 | F8: In review | G8: Smit | H8: Team finished coding — awaiting your review, then QA.
A9: V3 | B9: Creator performance | C9: Build the connection so vendors can see how their partnered creators are performing. | D9: App-side only | E9: Sprint 1 | F9: In review | G9: Smit | H9: Team finished coding — awaiting your review, then QA.
A10: V5 | B10: Partnerships & campaigns | C10: Point partnership / campaign requests at the correct server addresses so vendors can invite and manage creators. | D10: Needs backend path | E10: Sprint 2 | F10: In review | G10: Smit | H10: Addresses confirmed & remapped — awaiting review, then QA.
A11: V6 | B11: Product management | C11: Fix product view, stock-update and archive to use the correct server addresses. | D11: Needs backend path | E11: Sprint 2 | F11: In review | G11: Smit | H11: Addresses confirmed & corrected — awaiting review, then QA.
A12: V8 | B12: Sign-up: KYC documents | C12: Point KYC document upload and listing at the correct server addresses. | D12: Needs backend path | E12: Sprint 2 | F12: In review | G12: Smit | H12: Addresses confirmed & corrected — awaiting review, then QA.
A13: V7 | B13: Earnings & payouts | C13: Show the vendor earnings ledger and payout methods. | D13: Needs backend path | E13: Sprint 2 | F13: Blocked | G13: Backend | H13: Built our side; ledger & payout addresses still to confirm.
A14: V9 | B14: Matchmaking | C14: Show a creator-vendor compatibility score and let vendors invite matched creators. | D14: Needs backend path | E14: Sprint 2 | F14: Blocked | G14: Backend | H14: Built our side; addresses still to confirm.
A15: V10 | B15: Add product: image upload | C15: Let vendors upload product images when adding a product. | D15: Needs backend path | E15: Sprint 2 | F15: Blocked | G15: Backend | H15: Upload endpoint isn't available yet.
A16: V11 | B16: Order returns | C16: Let vendors process a return on an order. | D16: Needs backend path | E16: Sprint 2 | F16: Blocked | G16: Backend | H16: Return endpoint isn't available yet.
A17: V12 | B17: Brand Studio | C17: Enable campaign templates, campaign analytics and market insights. | D17: Needs new backend | E17: Sprint 3 | F17: Blocked | G17: Backend | H17: Screens built; all three features need new backend endpoints.
A18: V4 | B18: Help & support | C18: Connect the support screen so vendors can view and raise support tickets. The screen exists but isn't wired yet. | D18: App-side only | E18: Sprint 1 | F18: Not started | G18: App team | H18: Our team can start now — no backend dependency.
